colcon_argcomplete/__init__.py
colcon_argcomplete/argcomplete_completer/__init__.py
colcon_argcomplete/argument_parser/__init__.py
colcon_argcomplete/argument_parser/argcomplete/__init__.py
colcon_argcomplete/argument_parser/argcomplete/completer/__init__.py
colcon_argcomplete/argument_parser/argcomplete/completer/package_name.py
colcon_argcomplete-0.3.2.data/data/share/colcon_argcomplete/hook/colcon-argcomplete.bash
colcon_argcomplete-0.3.2.data/data/share/colcon_argcomplete/hook/colcon-argcomplete.zsh
colcon_argcomplete-0.3.2.dist-info/METADATA
colcon_argcomplete-0.3.2.dist-info/RECORD
colcon_argcomplete-0.3.2.dist-info/WHEEL
colcon_argcomplete-0.3.2.dist-info/entry_points.txt
colcon_argcomplete-0.3.2.dist-info/top_level.txt
